greppo/__init__.py
greppo/cli.py
greppo/colorbrewer.py
greppo/greppo.py
greppo/greppo_server.py
greppo/osm.py
greppo/user_script_utils.py
greppo/input_types/__init__.py
greppo/input_types/bar_chart.py
greppo/input_types/display.py
greppo/input_types/draw_feature.py
greppo/input_types/line_chart.py
greppo/input_types/multiselect.py
greppo/input_types/number.py
greppo/input_types/select.py
greppo/input_types/text.py
greppo/layers/__init__.py
greppo/layers/base_layer.py
greppo/layers/ee_layer.py
greppo/layers/image_layer.py
greppo/layers/overlay_layer.py
greppo/layers/raster_layer.py
greppo/layers/tile_layer.py
greppo/layers/vector_layer.py
greppo/layers/wms_tile_layer.py
greppo/static/favicon.png
greppo/static/index.html
greppo/static/css/app.a14da775.css
greppo/static/css/chunk-vendors.db50bcea.css
greppo/static/img/logo.824287d2.svg
greppo/static/img/marker.d242732c.svg
greppo/static/img/spritesheet.fd5728f2.svg
greppo/static/js/app.7529265e.js
greppo/static/js/app.7529265e.js.map
greppo/static/js/chunk-vendors.526a29f2.js
greppo/static/js/chunk-vendors.526a29f2.js.map
greppo-0.0.33.dist-info/METADATA
greppo-0.0.33.dist-info/WHEEL
greppo-0.0.33.dist-info/entry_points.txt
greppo-0.0.33.dist-info/top_level.txt
greppo-0.0.33.dist-info/RECORD
