Metadata-Version: 2.1
Name: greppo
Version: 0.0.33
Summary: Build responsive web-apps for geospatial applications.
Home-page: https://greppo.io/
Author: Adithya Krishnan and Sarma Tangirala
Author-email: greppomail@gmail.com
License: "Apache 2"
Project-URL: Source, https://github.com/greppo-io/greppo
Project-URL: Documentation, https://docs.greppo.io/
Classifier: Development Status :: 2 - Pre-Alpha
Classifier: Programming Language :: Python :: 3.9
Classifier: Operating System :: OS Independent
Requires-Python: >=3.6
Requires-Dist: click (==8.0.3)
Requires-Dist: geopandas (>=0.9.0)
Requires-Dist: pandas (>=1.1.5)
Requires-Dist: numpy
Requires-Dist: Shapely (==1.7.1)
Requires-Dist: starlette (==0.16.0)
Requires-Dist: uvicorn (==0.15.0)
Requires-Dist: meta (==1.0.2)
Requires-Dist: xyzservices
Requires-Dist: earthengine-api
